coding_converse/__init__.py
coding_converse/__main__.py
coding_converse/server.py
message_dialog/__init__.py
message_dialog/dialog_pyqt.py
coding_converse-0.1.3.dist-info/METADATA
coding_converse-0.1.3.dist-info/WHEEL
coding_converse-0.1.3.dist-info/entry_points.txt
coding_converse-0.1.3.dist-info/top_level.txt
coding_converse-0.1.3.dist-info/RECORD
